ipatests/__init__.py
ipatests-4.12.2.dist-info/METADATA
ipatests-4.12.2.dist-info/WHEEL
ipatests-4.12.2.dist-info/top_level.txt
ipatests-4.12.2.dist-info/RECORD
